timelined_array-0.1.2.dist-info/METADATA
timelined_array-0.1.2.dist-info/WHEEL
timelined_array-0.1.2.dist-info/entry_points.txt
timelined_array-0.1.2.dist-info/licenses/LICENSE
timelined_array/__init__.py
timelined_array/time.py
timelined_array-0.1.2.dist-info/RECORD
