Metadata-Version: 2.1
Name: timelined_array
Version: 0.1.2
Summary: Manage easily 1 or multidimensionnal samples numpy arrays that are time related. Extends numpy without removing any of it's abilities on such arrays.
Author-Email: Timothe Jost <44769559+JostTim@users.noreply.github.com>
License: MIT
Project-URL: Homepage, https://pypi.org/project/timelined_array/
Project-URL: Source, https://github.com/JostTim/timelined_array
Requires-Python: >=3.11
Requires-Dist: numpy>=2
